README.md
setup.py
coin_sdk/__init__.py
coin_sdk.egg-info/PKG-INFO
coin_sdk.egg-info/SOURCES.txt
coin_sdk.egg-info/dependency_links.txt
coin_sdk.egg-info/not-zip-safe
coin_sdk.egg-info/requires.txt
coin_sdk.egg-info/top_level.txt
coin_sdk/common/__init__.py
coin_sdk/common/config.py
coin_sdk/common/securityservice.py
coin_sdk/common/sendrequest.py
coin_sdk/mobile_connect/__init__.py
coin_sdk/mobile_connect/v3/__init__.py
coin_sdk/mobile_connect/v3/mcconfig.py
coin_sdk/mobile_connect/v3/sender.py
coin_sdk/mobile_connect/v3/domain/__init__.py
coin_sdk/mobile_connect/v3/domain/discovery_request.py
coin_sdk/mobile_connect/v3/domain/discovery_response.py
coin_sdk/mobile_connect/v3/domain/error_body.py
coin_sdk/mobile_connect/v3/domain/link.py
coin_sdk/mobile_connect/v3/domain/supported_services.py
coin_sdk/number_portability/__init__.py
coin_sdk/number_portability/domain.py
coin_sdk/number_portability/npconfig.py
coin_sdk/number_portability/receiver.py
coin_sdk/number_portability/sender.py
coin_sdk/number_portability/utils.py
coin_sdk/number_portability/messages/__init__.py
coin_sdk/number_portability/messages/message.py
coin_sdk/number_portability/messages/message_response.py
coin_sdk/number_portability/messages/activationservicenumber/__init__.py
coin_sdk/number_portability/messages/activationservicenumber/activation_service_number.py
coin_sdk/number_portability/messages/activationservicenumber/activation_service_number_body.py
coin_sdk/number_portability/messages/activationservicenumber/activation_service_number_builder.py
coin_sdk/number_portability/messages/activationservicenumber/activation_service_number_envelope.py
coin_sdk/number_portability/messages/activationservicenumber/activation_service_number_message.py
coin_sdk/number_portability/messages/activationservicenumber/activation_service_number_repeats.py
coin_sdk/number_portability/messages/activationservicenumber/activation_service_number_seq.py
coin_sdk/number_portability/messages/cancel/__init__.py
coin_sdk/number_portability/messages/cancel/cancel.py
coin_sdk/number_portability/messages/cancel/cancel_body.py
coin_sdk/number_portability/messages/cancel/cancel_builder.py
