Metadata-Version: 2.4
Name: coin_sdk
Version: 1.6.8
Summary: SDKs for Vereninging COIN's apis
Home-page: https://gitlab.com/verenigingcoin-public/coin-sdk-python
Author: Vereniging COIN
Author-email: devops@coin.nl
License: Apache-2.0
Keywords: COIN,Numberportability,TELECOM,SDK
Platform: any
Classifier: Development Status :: 5 - Production/Stable
Classifier: Intended Audience :: Developers
Classifier: Topic :: Software Development :: Libraries
Classifier: License :: OSI Approved :: MIT License
Classifier: Programming Language :: Python :: 3.9
Classifier: Programming Language :: Python :: 3.10
Classifier: Programming Language :: Python :: 3.11
Classifier: Programming Language :: Python :: 3.12
Requires-Python: >=3.9
Requires-Dist: requests>=2.32.3
Requires-Dist: cryptography>=45.0.2
Requires-Dist: pyjwt>=2.10.1
Requires-Dist: colorama>=0.4.6
Requires-Dist: sseclient-py>=1.8.0
Requires-Dist: six>=1.17.0
Dynamic: author
Dynamic: author-email
Dynamic: classifier
Dynamic: description
Dynamic: description-content-type
Dynamic: home-page
Dynamic: keywords
Dynamic: license
Dynamic: platform
Dynamic: requires-dist
Dynamic: requires-python
Dynamic: summary
